{
  "$schema": "https://mintlify.com/docs.json",
  "name": "Userplex",
  "logo": {
    "light": "/logo/light.svg",
    "dark": "/logo/dark.svg"
  },
  "favicon": "/favicon.svg",
  "colors": {
    "primary": "#16A34A",
    "light": "#07C983",
    "dark": "#15803D"
  },
  "navigation": {
    "groups": [
      {
        "group": "Getting Started",
        "pages": [
          "index",
          "quickstart"
        ]
      },
      {
        "group": "Essentials",
        "pages": [
          "essentials/logs",
          "essentials/identities",
          "essentials/visualization",
          "essentials/datasources"
        ]
      },
      {
        "group": "API Reference",
        "openapi": "https://api.userplex.com/openapi"
      }
    ]
  }
}
